ragtrain/__init__.py
ragtrain/test.py
ragtrain-0.0.1.dist-info/METADATA
ragtrain-0.0.1.dist-info/WHEEL
ragtrain-0.0.1.dist-info/licenses/LICENSE
ragtrain-0.0.1.dist-info/RECORD
